[{"pk": 1, "fields": {"first_name": "", "password": "pbkdf2_sha256$15000$7oWS4MzILasu$PoKyEPzMjIVAs965a8UyUaDWMeOXPTYyqlxQYi6pYMU=", "date_joined": "2015-06-30T21:50:06.912Z", "last_login": "2015-06-30T21:50:06.912Z", "is_active": true, "groups": [], "email": "", "user_permissions": [], "last_name": "", "username": "sensun", "is_superuser": true, "is_staff": true}, "model": "auth.user"}, {"pk": 2, "fields": {"first_name": "Fugit nulla consequatur mol", "password": "Rerum libero et velit enim aliquid sunt in molest", "date_joined": "2016-01-23T20:48:20.130Z", "last_login": "2013-01-17T00:22:54.131Z", "is_active": true, "groups": [], "email": "nhlcnuohsylqg@yz.uss", "user_permissions": [8, 9, 16], "last_name": "Commodi quia qu", "username": "sen", "is_superuser": false, "is_staff": false}, "model": "auth.user"}]